odoo/addons/website_event_questions_template/README.rst
odoo/addons/website_event_questions_template/__init__.py
odoo/addons/website_event_questions_template/__manifest__.py
odoo/addons/website_event_questions_template/i18n/es.po
odoo/addons/website_event_questions_template/i18n/website_event_questions_template.pot
odoo/addons/website_event_questions_template/models/__init__.py
odoo/addons/website_event_questions_template/models/event.py
odoo/addons/website_event_questions_template/models/event_question_template.py
odoo/addons/website_event_questions_template/readme/CONFIGURE.rst
odoo/addons/website_event_questions_template/readme/CONTRIBUTORS.rst
odoo/addons/website_event_questions_template/readme/DESCRIPTION.rst
odoo/addons/website_event_questions_template/readme/USAGE.rst
odoo/addons/website_event_questions_template/security/ir.model.access.csv
odoo/addons/website_event_questions_template/static/description/icon.png
odoo/addons/website_event_questions_template/static/description/index.html
odoo/addons/website_event_questions_template/tests/__init__.py
odoo/addons/website_event_questions_template/tests/test_website_event_questions_template.py
odoo/addons/website_event_questions_template/views/event_view.xml
odoo/addons/website_event_questions_template/views/website_event_questions_template_view.xml
odoo12_addon_website_event_questions_template-12.0.1.0.0.dist-info/METADATA
odoo12_addon_website_event_questions_template-12.0.1.0.0.dist-info/RECORD
odoo12_addon_website_event_questions_template-12.0.1.0.0.dist-info/WHEEL
odoo12_addon_website_event_questions_template-12.0.1.0.0.dist-info/top_level.txt
